supertouch/__init__.py
supertouch/cli.py
supertouch-0.1.2.dist-info/LICENSE.txt
supertouch-0.1.2.dist-info/METADATA
supertouch-0.1.2.dist-info/WHEEL
supertouch-0.1.2.dist-info/entry_points.txt
supertouch-0.1.2.dist-info/top_level.txt
supertouch-0.1.2.dist-info/RECORD
