Metadata-Version: 2.1
Name: supertouch
Version: 0.1.2
Summary: Easily create files and folders.
Home-page: https://github.com/afdezl/supertouch
Author-email: adrian@luengo.co
License: MIT
Platform: UNKNOWN
Requires-Python: >3.6
